odoo/addons/maintenance_equipment_sequence/README.rst
odoo/addons/maintenance_equipment_sequence/__init__.py
odoo/addons/maintenance_equipment_sequence/__manifest__.py
odoo/addons/maintenance_equipment_sequence/i18n/es.po
odoo/addons/maintenance_equipment_sequence/i18n/it.po
odoo/addons/maintenance_equipment_sequence/i18n/maintenance_equipment_sequence.pot
odoo/addons/maintenance_equipment_sequence/i18n/pt_BR.po
odoo/addons/maintenance_equipment_sequence/models/__init__.py
odoo/addons/maintenance_equipment_sequence/models/maintenance.py
odoo/addons/maintenance_equipment_sequence/readme/CONTRIBUTORS.rst
odoo/addons/maintenance_equipment_sequence/readme/DESCRIPTION.rst
odoo/addons/maintenance_equipment_sequence/static/description/icon.png
odoo/addons/maintenance_equipment_sequence/static/description/index.html
odoo/addons/maintenance_equipment_sequence/tests/__init__.py
odoo/addons/maintenance_equipment_sequence/tests/test_maintenance_equipment_sequence.py
odoo/addons/maintenance_equipment_sequence/views/maintenance_views.xml
odoo12_addon_maintenance_equipment_sequence-12.0.1.0.0.99.dev11.dist-info/METADATA
odoo12_addon_maintenance_equipment_sequence-12.0.1.0.0.99.dev11.dist-info/WHEEL
odoo12_addon_maintenance_equipment_sequence-12.0.1.0.0.99.dev11.dist-info/top_level.txt
odoo12_addon_maintenance_equipment_sequence-12.0.1.0.0.99.dev11.dist-info/RECORD
